pandas_chained_logging/__init__.py
pandas_chained_logging/accessor.py
pandas_chained_logging/types.py
pandas_chained_logging-0.1.0.dist-info/METADATA
pandas_chained_logging-0.1.0.dist-info/WHEEL
pandas_chained_logging-0.1.0.dist-info/RECORD
