Metadata-Version: 2.1
Name: pandas-chained-logging
Version: 0.1.0
Summary: Stay true to pandas method chaining by using this logging accessor
Author: Marwan Sarieddine
Author-email: sarieddine.marwan@gmail.com
Requires-Python: >=3.8,<4.0
Classifier: Programming Language :: Python :: 3
Classifier: Programming Language :: Python :: 3.8
Classifier: Programming Language :: Python :: 3.9
Classifier: Programming Language :: Python :: 3.10
Classifier: Programming Language :: Python :: 3.11
Requires-Dist: pandas (>=1.5.3,<2.0.0)
